setup.py
Yafailbahoqbmam/Yafailbahoqbmam.py
Yafailbahoqbmam/__init__.py
Yafailbahoqbmam.egg-info/PKG-INFO
Yafailbahoqbmam.egg-info/SOURCES.txt
Yafailbahoqbmam.egg-info/dependency_links.txt
Yafailbahoqbmam.egg-info/top_level.txt