Metadata-Version: 2.1
Name: Yafailbahoqbmam
Version: 1.4
Summary: Composable HTTP middleware for requests
Author: Yafailbahoqbmam
Classifier: Programming Language :: Python :: 3
